accounts/__init__.py
accounts/adapter.py
accounts/admin.py
accounts/apps.py
accounts/configurations.py
accounts/models.py
accounts/serializers.py
accounts/tests.py
accounts/urls.py
accounts/views.py
accounts/management/commands/init_authprovider.py
accounts/management/commands/init_pkg.py
accounts/management/commands/init_users.py
accounts/management/commands/__pycache__/init_users.cpython-39.pyc
accounts/migrations/0001_initial.py
accounts/migrations/__init__.py
django_accounts_package-1.2.1.dist-info/LICENSE
django_accounts_package-1.2.1.dist-info/METADATA
django_accounts_package-1.2.1.dist-info/WHEEL
django_accounts_package-1.2.1.dist-info/top_level.txt
django_accounts_package-1.2.1.dist-info/RECORD
