Metadata-Version: 2.1
Name: django-accounts-package
Version: 1.2.1
Summary: A Django app to conduct web-based authentication using Microsoft and Google authentaction tokens.
Home-page: https://github.com/MuhammadAlgshy/django-accounts-package.git
Author: Muhammad Algshy, Mohammad Yusuf
Author-email: malgshy@gmail.com, mhdalyusuf@gmail.com
License: MIT
Classifier: Environment :: Web Environment
Classifier: Framework :: Django :: 3.2
Classifier: Intended Audience :: Developers
Classifier: License :: OSI Approved :: MIT License
Classifier: Operating System :: OS Independent
Classifier: Programming Language :: Python :: 3.8
Classifier: Programming Language :: Python :: 3.9
Classifier: Topic :: Internet :: WWW/HTTP
Classifier: Topic :: Internet :: WWW/HTTP :: Dynamic Content
Requires-Python: >=3.8
License-File: LICENSE
Requires-Dist: Django (>=3.2)
